{"v":"5.7.5","fr":100,"ip":0,"op":526.6666666666666,"w":642,"h":642,"nm":"Comp 1","ddd":0,"assets":[{"id":"1","layers":[{"ddd":0,"ind":2,"ty":3,"nm":"","sr":1,"ks":{"o":{"a":0,"k":100,"ix":2},"r":{"a":0,"k":0,"ix":2},"p":{"a":0,"k":[10001.898000597954,10004.546999931335],"ix":2},"a":{"a":0,"k":[0,0],"ix":2},"s":{"a":0,"k":[50,50],"ix":2}},"ao":0,"ip":0,"op":526.6666666666666,"st":0,"bm":0,"hd":false},{"ddd":0,"ind":3,"ty":4,"nm":"Group 1","sr":1,"ks":{"o":{"a":0,"k":100,"ix":2},"r":{"a":0,"k":0,"ix":2},"p":{"a":0,"k":[0,0],"ix":2},"a":{"a":0,"k":[0,0],"ix":2},"s":{"a":0,"k":[100,100],"ix":2}},"ao":0,"hd":false,"parent":2,"shapes":[{"ty":"gr","hd":false,"it":[{"ty":"sh","hd":false,"d":1,"ks":{"a":1,"k":[{"t":337,"s":[{"c":false,"v":[[3.438,-0.004],[0.027,3.406],[0.01,3.421],[0.056,3.461],[-3.375,0.031],[-3.421,-0.01],[-3.397,-0.021],[0.014,-3.432],[-0.01,-3.421],[0.024,-3.444],[3.454,-0.013],[3.421,0.011],[3.438,-0.004]],"i":[[0,0],[0,0],[0,0],[0,0],[0,0],[0,0],[0,0],[0,0],[0,0],[0,0],[0,0],[0,0],[0,0]],"o":[[0,0],[0,0],[0,0],[0,0],[0,0],[0,0],[0,0],[0,0],[0,0],[0,0],[0,0],[0,0],[0,0]]}],"i":{"x":[1],"y":[1]},"o":{"x":[0],"y":[0]}},{"t":387,"s":[{"c":false,"v":[[12.204,8.794],[8.792,12.204],[0.01,3.422],[-8.706,12.137],[-12.137,8.707],[-3.421,-0.01],[-12.204,-8.793],[-8.792,-12.204],[-0.01,-3.421],[8.706,-12.137],[12.137,-8.706],[3.421,0.011],[12.204,8.794]],"i":[[0,0],[0,0],[0,0],[0,0],[0,0],[0,0],[0,0],[0,0],[0,0],[0,0],[0,0],[0,0],[0,0]],"o":[[0,0],[0,0],[0,0],[0,0],[0,0],[0,0],[0,0],[0,0],[0,0],[0,0],[0,0],[0,0],[0,0]]}],"i":{"x":[1],"y":[1]},"o":{"x":[0],"y":[0]}}],"ix":2}},{"ty":"fl","c":{"a":0,"k":[0.2901960784313726,0.788235294117647,0.49411764705882355],"ix":2},"o":{"a":0,"k":100,"ix":2},"r":1,"bm":0,"nm":"Fill 1","mn":"ADBE Vector Graphic - Fill","hd":false},{"ty":"tm","s":{"a":0,"k":0,"ix":2},"e":{"a":0,"k":100,"ix":2},"o":{"a":0,"k":0,"ix":2},"m":1,"hd":false},{"ty":"tr","hd":false,"p":{"a":0,"k":[46.174,44.297],"ix":2},"a":{"a":0,"k":[0,0],"ix":2},"s":{"a":0,"k":[100,100],"ix":2},"r":{"a":0,"k":0,"ix":2},"o":{"a":1,"k":[{"t":337,"s":[0],"i":{"x":[1],"y":[1]},"o":{"x":[0],"y":[0]}},{"t":342,"s":[100],"i":{"x":[1],"y":[1]},"o":{"x":[0],"y":[0]}}],"ix":2},"sk":{"a":0,"k":0,"ix":2},"sa":{"a":0,"k":0,"ix":2}}]}],"ip":0,"op":526.6666666666666,"st":0,"bm":0},{"ddd":0,"ind":4,"ty":4,"nm":"Group 2","sr":1,"ks":{"o":{"a":0,"k":100,"ix":2},"r":{"a":0,"k":0,"ix":2},"p":{"a":0,"k":[0,0],"ix":2},"a":{"a":0,"k":[0,0],"ix":2},"s":{"a":0,"k":[100,100],"ix":2}},"ao":0,"hd":false,"parent":2,"shapes":[{"ty":"gr","hd":false,"it":[{"ty":"sh","hd":false,"d":1,"ks":{"a":1,"k":[{"t":58,"s":[{"c":false,"v":[[0.001,36],[2.204,2.371],[0.001,-36],[-3.43,1.971],[0.001,36]],"i":[[-2.46,0.083],[-0.259,19.058],[1.377,0.116],[0,-19.883],[-2.46,0.083]],"o":[[3.106,-0.105],[0.271,-19.881],[-1.276,-0.107],[0,19.882],[3.106,-0.105]]}],"i":{"x":[1],"y":[1]},"o":{"x":[0],"y":[0]}},{"t":100,"s":[{"c":false,"v":[[0.001,36],[36.074,0],[0.001,-36],[-36.074,0],[0.001,36]],"i":[[-19.923,0],[0,19.882],[19.923,0],[0,-19.883],[-19.923,0]],"o":[[19.923,0],[0,-19.883],[-19.923,0],[0,19.882],[19.923,0]]}],"i":{"x":[1],"y":[1]},"o":{"x":[0],"y":[0]}},{"t":140,"s":[{"c":false,"v":[[0.001,36],[2.204,2.371],[0.001,-36],[-3.43,1.971],[0.001,36]],"i":[[-2.46,0.083],[-0.259,19.058],[1.377,0.116],[0,-19.883],[-2.46,0.083]],"o":[[3.106,-0.105],[0.271,-19.881],[-1.276,-0.107],[0,19.882],[3.106,-0.105]]}],"i":{"x":[1],"y":[1]},"o":{"x":[0],"y":[0]}},{"t":183,"s":[{"c":false,"v":[[0.001,36],[36.074,0],[0.001,-36],[-36.074,0],[0.001,36]],"i":[[-19.923,0],[0,19.882],[19.923,0],[0,-19.883],[-19.923,0]],"o":[[19.923,0],[0,-19.883],[-19.923,0],[0,19.882],[19.923,0]]}],"i":{"x":[1],"y":[1]},"o":{"x":[0],"y":[0]}},{"t":210,"s":[{"c":false,"v":[[0.001,36],[36.074,0],[0.001,-36],[-36.074,0],[0.001,36]],"i":[[-19.923,0],[0,19.882],[19.923,0],[0,-19.883],[-19.923,0]],"o":[[19.923,0],[0,-19.883],[-19.923,0],[0,19.882],[19.923,0]]}],"i":{"x":[1],"y":[1]},"o":{"x":[0],"y":[0]}},{"t":245,"s":[{"c":false,"v":[[0.001,36],[2.204,2.371],[0.001,-36],[-3.43,1.971],[0.001,36]],"i":[[-2.46,0.083],[-0.259,19.058],[1.377,0.116],[0,-19.883],[-2.46,0.083]],"o":[[3.106,-0.105],[0.271,-19.881],[-1.276,-0.107],[0,19.882],[3.106,-0.105]]}],"i":{"x":[1],"y":[1]},"o":{"x":[0],"y":[0]}},{"t":288,"s":[{"c":false,"v":[[0.001,36],[36.074,0],[0.001,-36],[-36.074,0],[0.001,36]],"i":[[-19.923,0],[0,19.882],[19.923,0],[0,-19.883],[-19.923,0]],"o":[[19.923,0],[0,-19.883],[-19.923,0],[0,19.882],[19.923,0]]}],"i":{"x":[1],"y":[1]},"o":{"x":[0],"y":[0]}}],"ix":2}},{"ty":"st","c":{"a":0,"k":[0.7137254901960784,0.9411764705882353,0.611764705882353],"ix":2},"o":{"a":0,"k":100,"ix":2},"w":{"a":1,"k":[{"t":58,"s":[5.6],"i":{"x":[1],"y":[1]},"o":{"x":[0],"y":[0]}},{"t":100,"s":[3.6],"i":{"x":[1],"y":[1]},"o":{"x":[0],"y":[0]}},{"t":140,"s":[5.6],"i":{"x":[1],"y":[1]},"o":{"x":[0],"y":[0]}},{"t":183,"s":[3.6],"i":{"x":[1],"y":[1]},"o":{"x":[0],"y":[0]}},{"t":210,"s":[3.6],"i":{"x":[1],"y":[1]},"o":{"x":[0],"y":[0]}},{"t":245,"s":[5.6],"i":{"x":[1],"y":[1]},"o":{"x":[0],"y":[0]}},{"t":288,"s":[3.6],"i":{"x":[1],"y":[1]},"o":{"x":[0],"y":[0]}}],"ix":2},"hd":false,"lc":2,"lj":2},{"ty":"fl","c":{"a":0,"k":[1,1,1],"ix":2},"o":{"a":0,"k":100,"ix":2},"r":1,"bm":0,"nm":"Fill 1","mn":"ADBE Vector Graphic - Fill","hd":false},{"ty":"tm","s":{"a":0,"k":0,"ix":2},"e":{"a":0,"k":100,"ix":2},"o":{"a":0,"k":0,"ix":2},"m":1,"hd":false},{"ty":"tr","hd":false,"p":{"a":0,"k":[45.07400131225586,45],"ix":2},"a":{"a":0,"k":[0,0],"ix":2},"s":{"a":0,"k":[100.0000000634859,100.0000000634859],"ix":2},"r":{"a":0,"k":-42.50000070477063,"ix":2},"o":{"a":0,"k":100,"ix":2},"sk":{"a":0,"k":0,"ix":2},"sa":{"a":0,"k":0,"ix":2}}]}],"ip":0,"op":526.6666666666666,"st":0,"bm":0},{"ddd":0,"ind":5,"ty":4,"nm":"Group 3","sr":1,"ks":{"o":{"a":0,"k":100,"ix":2},"r":{"a":0,"k":0,"ix":2},"p":{"a":0,"k":[10000,10000],"ix":2},"a":{"a":0,"k":[0,0],"ix":2},"s":{"a":0,"k":[100,100],"ix":2}},"ao":0,"hd":false,"shapes":[{"ty":"gr","hd":false,"it":[{"ty":"sh","hd":false,"d":1,"ks":{"a":0,"k":{"c":false,"v":[[-15.301,-15.277],[-8.483,-15.273],[15.305,8.476],[15.31,15.269],[15.302,15.277],[8.483,15.273],[-15.305,-8.475],[-15.31,-15.268],[-15.301,-15.277]],"i":[[0,0],[-1.883,-1.88],[0,0],[1.874,-1.878],[0,0],[1.884,1.881],[0,0],[-1.874,1.877],[0,0]],"o":[[1.885,-1.879],[0,0],[1.877,1.874],[0,0],[-1.885,1.878],[0,0],[-1.877,-1.875],[0,0],[1.885,-1.879]]}}},{"ty":"fl","c":{"a":0,"k":[0.2901960784313726,0.788235294117647,0.49411764705882355],"ix":2},"o":{"a":0,"k":100,"ix":2},"r":1,"bm":0,"nm":"Fill 1","mn":"ADBE Vector Graphic - Fill","hd":false},{"ty":"tm","s":{"a":0,"k":0,"ix":2},"e":{"a":0,"k":100,"ix":2},"o":{"a":0,"k":0,"ix":2},"m":1,"hd":false},{"ty":"tr","hd":false,"p":{"a":0,"k":[41.70899963378906,45.5],"ix":2},"a":{"a":0,"k":[0,0],"ix":2},"s":{"a":0,"k":[50,50],"ix":2},"r":{"a":0,"k":0,"ix":2},"o":{"a":0,"k":100,"ix":2},"sk":{"a":0,"k":0,"ix":2},"sa":{"a":0,"k":0,"ix":2}}]}],"ip":0,"op":526.6666666666666,"st":0,"bm":0}]},{"id":"2","layers":[{"ddd":0,"ind":7,"ty":4,"nm":"Group 1","sr":1,"ks":{"o":{"a":0,"k":100,"ix":2},"r":{"a":0,"k":0,"ix":2},"p":{"a":0,"k":[10000,10000],"ix":2},"a":{"a":0,"k":[0,0],"ix":2},"s":{"a":0,"k":[100,100],"ix":2}},"ao":0,"hd":false,"shapes":[{"ty":"gr","hd":false,"it":[{"ty":"sh","hd":false,"d":1,"ks":{"a":0,"k":{"c":false,"v":[[1.8,1.8],[70.211,1.8]],"i":[[0,0],[0,0]],"o":[[0,0],[0,0]]}}},{"ty":"st","c":{"a":0,"k":[0.7137254901960784,0.9411764705882353,0.611764705882353],"ix":2},"o":{"a":0,"k":100,"ix":2},"w":{"a":0,"k":3.6,"ix":2},"hd":false,"lc":2,"lj":2},{"ty":"tm","s":{"a":0,"k":0,"ix":2},"e":{"a":1,"k":[{"t":28,"s":[0],"i":{"x":[1],"y":[1]},"o":{"x":[0],"y":[0]}},{"t":65,"s":[100],"i":{"x":[1],"y":[1]},"o":{"x":[0],"y":[0]}}],"ix":2},"o":{"a":0,"k":0,"ix":2},"m":1,"hd":false},{"ty":"tr","hd":false,"p":{"a":0,"k":[227.8080139160156,221.2169952392578],"ix":2},"a":{"a":0,"k":[0,0],"ix":2},"s":{"a":0,"k":[200,200],"ix":2},"r":{"a":0,"k":0,"ix":2},"o":{"a":0,"k":100,"ix":2},"sk":{"a":0,"k":0,"ix":2},"sa":{"a":0,"k":0,"ix":2}}]}],"ip":0,"op":526.6666666666666,"st":0,"bm":0}]},{"id":"3","layers":[{"ddd":0,"ind":9,"ty":4,"nm":"Group 1","sr":1,"ks":{"o":{"a":0,"k":100,"ix":2},"r":{"a":0,"k":0,"ix":2},"p":{"a":0,"k":[10000,10000],"ix":2},"a":{"a":0,"k":[0,0],"ix":2},"s":{"a":0,"k":[100,100],"ix":2}},"ao":0,"hd":false,"shapes":[{"ty":"gr","hd":false,"it":[{"ty":"sh","hd":false,"d":1,"ks":{"a":0,"k":{"c":false,"v":[[1.8,1.8],[63.125,1.8]],"i":[[0,0],[0,0]],"o":[[0,0],[0,0]]}}},{"ty":"st","c":{"a":0,"k":[0.7137254901960784,0.9411764705882353,0.611764705882353],"ix":2},"o":{"a":0,"k":100,"ix":2},"w":{"a":0,"k":3.6,"ix":2},"hd":false,"lc":2,"lj":2},{"ty":"tm","s":{"a":0,"k":0,"ix":2},"e":{"a":1,"k":[{"t":40,"s":[0],"i":{"x":[1],"y":[1]},"o":{"x":[0],"y":[0]}},{"t":77,"s":[100],"i":{"x":[1],"y":[1]},"o":{"x":[0],"y":[0]}}],"ix":2},"o":{"a":0,"k":0,"ix":2},"m":1,"hd":false},{"ty":"tr","hd":false,"p":{"a":0,"k":[227.8080139160156,275.2169799804688],"ix":2},"a":{"a":0,"k":[0,0],"ix":2},"s":{"a":0,"k":[200,200],"ix":2},"r":{"a":0,"k":0,"ix":2},"o":{"a":0,"k":100,"ix":2},"sk":{"a":0,"k":0,"ix":2},"sa":{"a":0,"k":0,"ix":2}}]}],"ip":0,"op":526.6666666666666,"st":0,"bm":0}]},{"id":"4","layers":[{"ddd":0,"ind":11,"ty":4,"nm":"Group 1","sr":1,"ks":{"o":{"a":0,"k":100,"ix":2},"r":{"a":0,"k":0,"ix":2},"p":{"a":0,"k":[10000,10000],"ix":2},"a":{"a":0,"k":[0,0],"ix":2},"s":{"a":0,"k":[100,100],"ix":2}},"ao":0,"hd":false,"shapes":[{"ty":"gr","hd":false,"it":[{"ty":"sh","hd":false,"d":1,"ks":{"a":0,"k":{"c":false,"v":[[1.8,1.8],[28.855,1.8]],"i":[[0,0],[0,0]],"o":[[0,0],[0,0]]}}},{"ty":"st","c":{"a":0,"k":[0.7137254901960784,0.9411764705882353,0.611764705882353],"ix":2},"o":{"a":0,"k":100,"ix":2},"w":{"a":0,"k":3.6,"ix":2},"hd":false,"lc":2,"lj":2},{"ty":"tm","s":{"a":0,"k":0,"ix":2},"e":{"a":1,"k":[{"t":52,"s":[0],"i":{"x":[1],"y":[1]},"o":{"x":[0],"y":[0]}},{"t":88,"s":[100],"i":{"x":[1],"y":[1]},"o":{"x":[0],"y":[0]}}],"ix":2},"o":{"a":0,"k":0,"ix":2},"m":1,"hd":false},{"ty":"tr","hd":false,"p":{"a":0,"k":[227.8099822998047,325.6179809570312],"ix":2},"a":{"a":0,"k":[0,0],"ix":2},"s":{"a":0,"k":[200,200],"ix":2},"r":{"a":0,"k":0,"ix":2},"o":{"a":0,"k":100,"ix":2},"sk":{"a":0,"k":0,"ix":2},"sa":{"a":0,"k":0,"ix":2}}]}],"ip":0,"op":526.6666666666666,"st":0,"bm":0}]},{"id":"5","layers":[{"ddd":0,"ind":13,"ty":4,"nm":"Group 1","sr":1,"ks":{"o":{"a":0,"k":100,"ix":2},"r":{"a":0,"k":0,"ix":2},"p":{"a":0,"k":[10000,10000],"ix":2},"a":{"a":0,"k":[0,0],"ix":2},"s":{"a":0,"k":[100,100],"ix":2}},"ao":0,"hd":false,"shapes":[{"ty":"gr","hd":false,"it":[{"ty":"sh","hd":false,"d":1,"ks":{"a":0,"k":{"c":false,"v":[[1.8,1.8],[28.855,1.8]],"i":[[0,0],[0,0]],"o":[[0,0],[0,0]]}}},{"ty":"st","c":{"a":0,"k":[0.7137254901960784,0.9411764705882353,0.611764705882353],"ix":2},"o":{"a":0,"k":100,"ix":2},"w":{"a":0,"k":3.6,"ix":2},"hd":false,"lc":2,"lj":2},{"ty":"tm","s":{"a":0,"k":0,"ix":2},"e":{"a":1,"k":[{"t":63,"s":[0],"i":{"x":[1],"y":[1]},"o":{"x":[0],"y":[0]}},{"t":100,"s":[100],"i":{"x":[1],"y":[1]},"o":{"x":[0],"y":[0]}}],"ix":2},"o":{"a":0,"k":0,"ix":2},"m":1,"hd":false},{"ty":"tr","hd":false,"p":{"a":0,"k":[227.8099822998047,376.0180053710938],"ix":2},"a":{"a":0,"k":[0,0],"ix":2},"s":{"a":0,"k":[200,200],"ix":2},"r":{"a":0,"k":0,"ix":2},"o":{"a":0,"k":100,"ix":2},"sk":{"a":0,"k":0,"ix":2},"sa":{"a":0,"k":0,"ix":2}}]}],"ip":0,"op":526.6666666666666,"st":0,"bm":0}]},{"id":"8","layers":[{"ddd":0,"ind":15,"ty":3,"nm":"","sr":1,"ks":{"o":{"a":0,"k":100,"ix":2},"r":{"a":0,"k":0,"ix":2},"p":{"a":0,"k":[10000,10000],"ix":2},"a":{"a":0,"k":[0,0],"ix":2},"s":{"a":0,"k":[100,100],"ix":2}},"ao":0,"ip":0,"op":526.6666666666666,"st":0,"bm":0,"hd":false},{"ddd":0,"refId":"6","w":20000,"h":20000,"ind":17,"ty":0,"nm":"parent sombra (In/Out)","sr":1,"ks":{"o":{"a":1,"k":[{"t":56,"s":[0],"i":{"x":[1],"y":[1]},"o":{"x":[0],"y":[0]}},{"t":57,"s":[100],"i":{"x":[1],"y":[1]},"o":{"x":[0],"y":[0]}},{"t":21077,"s":[100],"i":{"x":[1],"y":[1]},"o":{"x":[0],"y":[0]}},{"t":21078,"s":[0],"i":{"x":[1],"y":[1]},"o":{"x":[0],"y":[0]}}],"ix":2},"r":{"a":0,"k":0,"ix":2},"p":{"a":0,"k":[0,0],"ix":2},"a":{"a":0,"k":[10000,10000],"ix":2},"s":{"a":0,"k":[100,100],"ix":2}},"ao":0,"ip":0,"op":526.6666666666666,"st":0,"bm":0,"hd":false,"parent":15},{"ddd":0,"ind":18,"ty":3,"nm":"","sr":1,"ks":{"o":{"a":0,"k":100,"ix":2},"r":{"a":1,"k":[{"t":57,"s":[64],"i":{"x":[1],"y":[1]},"o":{"x":[0],"y":[0]}},{"t":153,"s":[23],"i":{"x":[1],"y":[1]},"o":{"x":[0],"y":[0]}},{"t":222,"s":[-21],"i":{"x":[1],"y":[1]},"o":{"x":[0],"y":[0]}},{"t":305,"s":[16],"i":{"x":[1],"y":[1]},"o":{"x":[0],"y":[0]}},{"t":367,"s":[0],"i":{"x":[1],"y":[1]},"o":{"x":[0],"y":[0]}}],"ix":2},"p":{"a":1,"k":[{"t":57,"s":[240.252,377.045],"i":{"x":[1],"y":[1]},"o":{"x":[0],"y":[0]}},{"t":147,"s":[323.752,265.045],"i":{"x":[1],"y":[1]},"o":{"x":[0],"y":[0]}},{"t":222,"s":[334.252,403.045],"i":{"x":[1],"y":[1]},"o":{"x":[0],"y":[0]}},{"t":305,"s":[499.252,415.045],"i":{"x":[1],"y":[1]},"o":{"x":[0],"y":[0]}}],"ix":2},"a":{"a":0,"k":[47.206,48.054],"ix":2},"s":{"a":1,"k":[{"t":57,"s":[0,0],"i":{"x":[1],"y":[1]},"o":{"x":[0],"y":[0]}},{"t":100,"s":[240,240],"i":{"x":[1],"y":[1]},"o":{"x":[0],"y":[0]}},{"t":222,"s":[240,240],"i":{"x":[1],"y":[1]},"o":{"x":[0],"y":[0]}},{"t":305,"s":[400,400],"i":{"x":[1],"y":[1]},"o":{"x":[0],"y":[0]}}],"ix":2}},"ao":0,"ip":0,"op":526.6666666666666,"st":0,"bm":0,"hd":false,"parent":15},{"ddd":0,"refId":"7","w":20000,"h":20000,"ind":26,"ty":0,"nm":"LUPA sombra (In/Out)","sr":1,"ks":{"o":{"a":1,"k":[{"t":56,"s":[0],"i":{"x":[1],"y":[1]},"o":{"x":[0],"y":[0]}},{"t":57,"s":[100],"i":{"x":[1],"y":[1]},"o":{"x":[0],"y":[0]}},{"t":701,"s":[100],"i":{"x":[1],"y":[1]},"o":{"x":[0],"y":[0]}},{"t":702,"s":[0],"i":{"x":[1],"y":[1]},"o":{"x":[0],"y":[0]}}],"ix":2},"r":{"a":0,"k":0,"ix":2},"p":{"a":0,"k":[0,0],"ix":2},"a":{"a":0,"k":[10000,10000],"ix":2},"s":{"a":0,"k":[100,100],"ix":2}},"ao":0,"ip":0,"op":526.6666666666666,"st":0,"bm":0,"hd":false,"parent":18}]},{"id":"9","layers":[{"ddd":0,"ind":27,"ty":4,"nm":"Mask 1 (Mask)","sr":1,"ks":{"o":{"a":0,"k":100,"ix":2},"r":{"a":0,"k":0,"ix":2},"p":{"a":0,"k":[10000,10000],"ix":2},"a":{"a":0,"k":[0,0],"ix":2},"s":{"a":0,"k":[100,100],"ix":2}},"td":1,"ao":0,"hd":false,"shapes":[{"ty":"gr","hd":false,"it":[{"ty":"sh","hd":false,"d":1,"ks":{"a":0,"k":{"c":false,"v":[[412.5,169.5],[231.5,169.5],[202,190.5],[191,254],[191,428.5],[329,428.5],[333.5,434.5],[365.5,478.5],[399,436.5],[399,193],[412.5,169.5]],"i":[[-7.5,3.5],[0,0],[0,0],[0,0],[0,0],[-4,0],[0,-2.5],[-29.5,0],[0,15],[0,5],[-7.5,3.5]],"o":[[-13,0],[0,0],[0,0],[0,0],[0,0],[4,0],[0,2.5],[29.5,0],[0,-15],[0,-5],[-13,0]]}}},{"ty":"fl","c":{"a":0,"k":[0,0,0],"ix":2},"o":{"a":0,"k":100,"ix":2},"r":1,"bm":0,"nm":"Fill 1","mn":"ADBE Vector Graphic - Fill","hd":false},{"ty":"tm","s":{"a":0,"k":0,"ix":2},"e":{"a":0,"k":100,"ix":2},"o":{"a":0,"k":0,"ix":2},"m":1,"hd":false},{"ty":"tr","hd":false,"p":{"a":0,"k":[0,0],"ix":2},"a":{"a":0,"k":[0,0],"ix":2},"s":{"a":0,"k":[100,100],"ix":2},"r":{"a":0,"k":0,"ix":2},"o":{"a":0,"k":100,"ix":2},"sk":{"a":0,"k":0,"ix":2},"sa":{"a":0,"k":0,"ix":2}}]}],"ip":0,"op":526.6666666666666,"st":0,"bm":0},{"ddd":0,"refId":"8","w":20000,"h":20000,"ind":1,"ty":0,"nm":"Sombra lupa (Masked Group)","sr":1,"ks":{"o":{"a":0,"k":100,"ix":2},"r":{"a":0,"k":0,"ix":2},"p":{"a":0,"k":[10000,10000],"ix":2},"a":{"a":0,"k":[10000,10000],"ix":2},"s":{"a":0,"k":[100,100],"ix":2}},"ao":0,"ip":0,"op":526.6666666666666,"st":0,"bm":0,"hd":false,"parent":0,"tt":1}]},{"id":"6","layers":[{"ddd":0,"ind":16,"ty":3,"nm":"","sr":1,"ks":{"o":{"a":0,"k":100,"ix":2},"r":{"a":1,"k":[{"t":57,"s":[64],"i":{"x":[1],"y":[1]},"o":{"x":[0],"y":[0]}},{"t":153,"s":[23],"i":{"x":[1],"y":[1]},"o":{"x":[0],"y":[0]}},{"t":222,"s":[-21],"i":{"x":[1],"y":[1]},"o":{"x":[0],"y":[0]}},{"t":305,"s":[16],"i":{"x":[1],"y":[1]},"o":{"x":[0],"y":[0]}},{"t":367,"s":[0],"i":{"x":[1],"y":[1]},"o":{"x":[0],"y":[0]}}],"ix":2},"p":{"a":1,"k":[{"t":57,"s":[10240.252,10377.045],"i":{"x":[1],"y":[1]},"o":{"x":[0],"y":[0]}},{"t":147,"s":[10323.752,10265.045],"i":{"x":[1],"y":[1]},"o":{"x":[0],"y":[0]}},{"t":222,"s":[10334.252,10403.045],"i":{"x":[1],"y":[1]},"o":{"x":[0],"y":[0]}},{"t":305,"s":[10499.252,10415.045],"i":{"x":[1],"y":[1]},"o":{"x":[0],"y":[0]}}],"ix":2},"a":{"a":0,"k":[47.206,48.054],"ix":2},"s":{"a":1,"k":[{"t":57,"s":[0,0],"i":{"x":[1],"y":[1]},"o":{"x":[0],"y":[0]}},{"t":100,"s":[240,240],"i":{"x":[1],"y":[1]},"o":{"x":[0],"y":[0]}},{"t":222,"s":[240,240],"i":{"x":[1],"y":[1]},"o":{"x":[0],"y":[0]}},{"t":305,"s":[400,400],"i":{"x":[1],"y":[1]},"o":{"x":[0],"y":[0]}}],"ix":2}},"ao":0,"ip":0,"op":526.6666666666666,"st":0,"bm":0,"hd":false}]},{"id":"7","layers":[{"ddd":0,"ind":19,"ty":3,"nm":"","sr":1,"ks":{"o":{"a":0,"k":100,"ix":2},"r":{"a":0,"k":0,"ix":2},"p":{"a":0,"k":[10026.162,10029.375],"ix":2},"a":{"a":1,"k":[{"t":222,"s":[59.528,35.656],"i":{"x":[1],"y":[1]},"o":{"x":[0],"y":[0]}},{"t":305,"s":[55.428,43.556],"i":{"x":[1],"y":[1]},"o":{"x":[0],"y":[0]}}],"ix":2},"s":{"a":0,"k":[50,50],"ix":2}},"ao":0,"ip":0,"op":526.6666666666666,"st":0,"bm":0,"hd":false},{"ddd":0,"ind":20,"ty":3,"nm":"","sr":1,"ks":{"o":{"a":0,"k":100,"ix":2},"r":{"a":0,"k":0,"ix":2},"p":{"a":0,"k":[0,0],"ix":2},"a":{"a":0,"k":[0,0],"ix":2},"s":{"a":0,"k":[100,100],"ix":2}},"ao":0,"ip":0,"op":526.6666666666666,"st":0,"bm":0,"hd":false,"parent":19},{"ddd":0,"ind":21,"ty":3,"nm":"","sr":1,"ks":{"o":{"a":0,"k":100,"ix":2},"r":{"a":0,"k":0,"ix":2},"p":{"a":0,"k":[0,0],"ix":2},"a":{"a":0,"k":[0,0],"ix":2},"s":{"a":0,"k":[100,100],"ix":2}},"ao":0,"ip":0,"op":526.6666666666666,"st":0,"bm":0,"hd":false,"parent":20},{"ddd":0,"ind":22,"ty":3,"nm":"","sr":1,"ks":{"o":{"a":0,"k":100,"ix":2},"r":{"a":0,"k":-42.5,"ix":2},"p":{"a":0,"k":[45.074,45],"ix":2},"a":{"a":0,"k":[0,0],"ix":2},"s":{"a":0,"k":[100,100],"ix":2}},"ao":0,"ip":0,"op":526.6666666666666,"st":0,"bm":0,"hd":false,"parent":21},{"ddd":0,"ind":23,"ty":4,"nm":"Path","sr":1,"ks":{"o":{"a":0,"k":100,"ix":2},"r":{"a":0,"k":0,"ix":2},"p":{"a":0,"k":[0,0],"ix":2},"a":{"a":0,"k":[0,0],"ix":2},"s":{"a":0,"k":[100,100],"ix":2}},"ao":0,"hd":false,"parent":22,"shapes":[{"ty":"gr","hd":false,"it":[{"ty":"sh","hd":false,"d":1,"ks":{"a":1,"k":[{"t":58,"s":[{"c":false,"v":[[0.001,36],[2.204,2.371],[0.001,-36],[-3.43,1.971],[0.001,36]],"i":[[-2.46,0.083],[-0.259,19.058],[1.377,0.116],[0,-19.883],[-2.46,0.083]],"o":[[3.106,-0.105],[0.271,-19.881],[-1.276,-0.107],[0,19.882],[3.106,-0.105]]}],"i":{"x":[1],"y":[1]},"o":{"x":[0],"y":[0]}},{"t":100,"s":[{"c":false,"v":[[0.001,36],[36.074,0],[0.001,-36],[-36.074,0],[0.001,36]],"i":[[-19.923,0],[0,19.882],[19.923,0],[0,-19.883],[-19.923,0]],"o":[[19.923,0],[0,-19.883],[-19.923,0],[0,19.882],[19.923,0]]}],"i":{"x":[1],"y":[1]},"o":{"x":[0],"y":[0]}},{"t":140,"s":[{"c":false,"v":[[0.001,36],[2.204,2.371],[0.001,-36],[-3.43,1.971],[0.001,36]],"i":[[-2.46,0.083],[-0.259,19.058],[1.377,0.116],[0,-19.883],[-2.46,0.083]],"o":[[3.106,-0.105],[0.271,-19.881],[-1.276,-0.107],[0,19.882],[3.106,-0.105]]}],"i":{"x":[1],"y":[1]},"o":{"x":[0],"y":[0]}},{"t":183,"s":[{"c":false,"v":[[0.001,36],[36.074,0],[0.001,-36],[-36.074,0],[0.001,36]],"i":[[-19.923,0],[0,19.882],[19.923,0],[0,-19.883],[-19.923,0]],"o":[[19.923,0],[0,-19.883],[-19.923,0],[0,19.882],[19.923,0]]}],"i":{"x":[1],"y":[1]},"o":{"x":[0],"y":[0]}},{"t":210,"s":[{"c":false,"v":[[0.001,36],[36.074,0],[0.001,-36],[-36.074,0],[0.001,36]],"i":[[-19.923,0],[0,19.882],[19.923,0],[0,-19.883],[-19.923,0]],"o":[[19.923,0],[0,-19.883],[-19.923,0],[0,19.882],[19.923,0]]}],"i":{"x":[1],"y":[1]},"o":{"x":[0],"y":[0]}},{"t":245,"s":[{"c":false,"v":[[0.001,36],[2.204,2.371],[0.001,-36],[-3.43,1.971],[0.001,36]],"i":[[-2.46,0.083],[-0.259,19.058],[1.377,0.116],[0,-19.883],[-2.46,0.083]],"o":[[3.106,-0.105],[0.271,-19.881],[-1.276,-0.107],[0,19.882],[3.106,-0.105]]}],"i":{"x":[1],"y":[1]},"o":{"x":[0],"y":[0]}},{"t":288,"s":[{"c":false,"v":[[0.001,36],[36.074,0],[0.001,-36],[-36.074,0],[0.001,36]],"i":[[-19.923,0],[0,19.882],[19.923,0],[0,-19.883],[-19.923,0]],"o":[[19.923,0],[0,-19.883],[-19.923,0],[0,19.882],[19.923,0]]}],"i":{"x":[1],"y":[1]},"o":{"x":[0],"y":[0]}}],"ix":2}},{"ty":"st","c":{"a":0,"k":[0.792156862745098,0.8470588235294118,0.9137254901960784],"ix":2},"o":{"a":0,"k":100,"ix":2},"w":{"a":1,"k":[{"t":58,"s":[5.6],"i":{"x":[1],"y":[1]},"o":{"x":[0],"y":[0]}},{"t":100,"s":[3.6],"i":{"x":[1],"y":[1]},"o":{"x":[0],"y":[0]}},{"t":140,"s":[5.6],"i":{"x":[1],"y":[1]},"o":{"x":[0],"y":[0]}},{"t":183,"s":[3.6],"i":{"x":[1],"y":[1]},"o":{"x":[0],"y":[0]}},{"t":210,"s":[3.6],"i":{"x":[1],"y":[1]},"o":{"x":[0],"y":[0]}},{"t":245,"s":[5.6],"i":{"x":[1],"y":[1]},"o":{"x":[0],"y":[0]}},{"t":288,"s":[3.6],"i":{"x":[1],"y":[1]},"o":{"x":[0],"y":[0]}}],"ix":2},"hd":false,"lc":2,"lj":2},{"ty":"fl","c":{"a":0,"k":[0.792156862745098,0.8470588235294118,0.9137254901960784],"ix":2},"o":{"a":0,"k":100,"ix":2},"r":1,"bm":0,"nm":"Fill 1","mn":"ADBE Vector Graphic - Fill","hd":false},{"ty":"tm","s":{"a":0,"k":0,"ix":2},"e":{"a":0,"k":100,"ix":2},"o":{"a":0,"k":0,"ix":2},"m":1,"hd":false},{"ty":"tr","hd":false,"p":{"a":0,"k":[0,0],"ix":2},"a":{"a":0,"k":[0,0],"ix":2},"s":{"a":0,"k":[100,100],"ix":2},"r":{"a":0,"k":0,"ix":2},"o":{"a":0,"k":100,"ix":2},"sk":{"a":0,"k":0,"ix":2},"sa":{"a":0,"k":0,"ix":2}}]}],"ip":0,"op":526.6666666666666,"st":0,"bm":0},{"ddd":0,"ind":24,"ty":3,"nm":"","sr":1,"ks":{"o":{"a":0,"k":100,"ix":2},"r":{"a":0,"k":0,"ix":2},"p":{"a":0,"k":[79.622,81.906],"ix":2},"a":{"a":0,"k":[0,0],"ix":2},"s":{"a":0,"k":[100,100],"ix":2}},"ao":0,"ip":0,"op":526.6666666666666,"st":0,"bm":0,"hd":false,"parent":20},{"ddd":0,"ind":25,"ty":4,"nm":"Path","sr":1,"ks":{"o":{"a":0,"k":100,"ix":2},"r":{"a":0,"k":0,"ix":2},"p":{"a":0,"k":[0,0],"ix":2},"a":{"a":0,"k":[0,0],"ix":2},"s":{"a":0,"k":[100,100],"ix":2}},"ao":0,"hd":false,"parent":24,"shapes":[{"ty":"gr","hd":false,"it":[{"ty":"sh","hd":false,"d":1,"ks":{"a":0,"k":{"c":false,"v":[[-15.301,-15.277],[-8.483,-15.273],[15.305,8.476],[15.31,15.269],[15.302,15.277],[8.483,15.273],[-15.305,-8.475],[-15.31,-15.268],[-15.301,-15.277]],"i":[[0,0],[-1.883,-1.88],[0,0],[1.874,-1.878],[0,0],[1.884,1.881],[0,0],[-1.874,1.877],[0,0]],"o":[[1.885,-1.879],[0,0],[1.877,1.874],[0,0],[-1.885,1.878],[0,0],[-1.877,-1.875],[0,0],[1.885,-1.879]]}}},{"ty":"fl","c":{"a":0,"k":[0.792156862745098,0.8470588235294118,0.9137254901960784],"ix":2},"o":{"a":0,"k":100,"ix":2},"r":1,"bm":0,"nm":"Fill 1","mn":"ADBE Vector Graphic - Fill","hd":false},{"ty":"tm","s":{"a":0,"k":0,"ix":2},"e":{"a":0,"k":100,"ix":2},"o":{"a":0,"k":0,"ix":2},"m":1,"hd":false},{"ty":"tr","hd":false,"p":{"a":0,"k":[0,0],"ix":2},"a":{"a":0,"k":[0,0],"ix":2},"s":{"a":0,"k":[100,100],"ix":2},"r":{"a":0,"k":0,"ix":2},"o":{"a":0,"k":100,"ix":2},"sk":{"a":0,"k":0,"ix":2},"sa":{"a":0,"k":0,"ix":2}}]}],"ip":0,"op":526.6666666666666,"st":0,"bm":0}]},{"id":"12","layers":[{"ddd":0,"refId":"11","w":20000,"h":20000,"ind":35,"ty":0,"nm":"papel bot Outlines (Masked Group)","sr":1,"ks":{"o":{"a":0,"k":100,"ix":2},"r":{"a":0,"k":0,"ix":2},"p":{"a":0,"k":[9991.139,10353.102],"ix":2},"a":{"a":0,"k":[10057.389,10018.529],"ix":2},"s":{"a":0,"k":[200,200],"ix":2}},"ao":0,"ip":0,"op":526.6666666666666,"st":0,"bm":0,"hd":false}]},{"id":"10","layers":[{"ddd":0,"ind":30,"ty":3,"nm":"","sr":1,"ks":{"o":{"a":0,"k":100,"ix":2},"r":{"a":0,"k":0,"ix":2},"p":{"a":0,"k":[10000,10000],"ix":2},"a":{"a":0,"k":[0,0],"ix":2},"s":{"a":0,"k":[100,100],"ix":2}},"ao":0,"ip":0,"op":526.6666666666666,"st":0,"bm":0,"hd":false},{"ddd":0,"ind":31,"ty":3,"nm":"","sr":1,"ks":{"o":{"a":0,"k":100,"ix":2},"r":{"a":0,"k":0,"ix":2},"p":{"a":0,"k":[0,0],"ix":2},"a":{"a":0,"k":[0,0],"ix":2},"s":{"a":0,"k":[100,100],"ix":2}},"ao":0,"ip":0,"op":526.6666666666666,"st":0,"bm":0,"hd":false,"parent":30},{"ddd":0,"ind":32,"ty":3,"nm":"","sr":1,"ks":{"o":{"a":0,"k":100,"ix":2},"r":{"a":0,"k":0,"ix":2},"p":{"a":0,"k":[58.74,18.119],"ix":2},"a":{"a":0,"k":[0,0],"ix":2},"s":{"a":0,"k":[100,100],"ix":2}},"ao":0,"ip":0,"op":526.6666666666666,"st":0,"bm":0,"hd":false,"parent":31},{"ddd":0,"ind":33,"ty":4,"nm":"Path","sr":1,"ks":{"o":{"a":0,"k":100,"ix":2},"r":{"a":0,"k":0,"ix":2},"p":{"a":0,"k":[0,0],"ix":2},"a":{"a":0,"k":[0,0],"ix":2},"s":{"a":0,"k":[100,100],"ix":2}},"ao":0,"hd":false,"parent":32,"shapes":[{"ty":"gr","hd":false,"it":[{"ty":"sh","hd":false,"d":1,"ks":{"a":0,"k":{"c":false,"v":[[89.342,-145.931],[88.309,-145.931],[72.188,-128.68],[72.188,-128.419],[72.188,-6.1],[58.594,11.617],[53.059,11.617],[39.481,-6.211],[39.481,-9.933],[36.734,-12.743],[19.195,-12.743],[5.094,-12.743],[-16.645,-12.743],[-39.406,-12.743],[-53.01,-12.743],[-55.777,-9.951],[-55.777,-6.006],[-32.146,17.869],[-32.111,17.869],[-2.276,17.869],[54.109,17.869],[56.268,17.776],[59.46,17.237],[77.777,-6.006],[77.777,-128.586],[77.777,-128.717],[88.365,-140.254],[89.398,-140.254],[101.02,-128.531],[101.02,-115.262],[103.787,-115.262],[106.555,-118.053],[106.555,-128.531],[89.454,-145.931],[89.342,-145.931]],"i":[[0,0],[0,0],[0.013,-9.145],[0,0],[0,0],[7.994,-2.105],[1.814,0.473],[-0.022,8.366],[0,0],[1.528,0.009],[0,0],[0,0],[0,0],[0,0],[0,0],[0,-1.541],[0,0],[-13.061,-0.011],[0,0],[0,0],[0,0],[-0.609,0.093],[-1.049,0.261],[-0.013,11.099],[0,0],[0,0],[-5.938,0.542],[-0.345,-0.019],[-0.011,-6.47],[0,0],[0,0],[0,1.541],[0,0],[9.485,0.042],[0,0]],"o":[[0,0],[-9.048,0.552],[0,0],[0,0],[-0.017,8.335],[-1.815,0.473],[-8.019,-2.135],[0,0],[0.011,-1.541],[0,0],[0,0],[0,0],[0,0],[0,0],[-1.527,0],[0,0],[-0.012,13.175],[0,0],[0,0],[0,0],[0.609,0],[1.076,-0.099],[10.716,-2.516],[0,0],[0,0],[0.079,-6.014],[0.344,-0.019],[6.414,0.01],[0,0],[0,0],[1.528,0],[0,0],[0.04,-9.569],[0,0],[0,0]]}}},{"ty":"fl","c":{"a":0,"k":[0.9019607843137255,0.9019607843137255,0.9019607843137255],"ix":2},"o":{"a":0,"k":100,"ix":2},"r":1,"bm":0,"nm":"Fill 1","mn":"ADBE Vector Graphic - Fill","hd":false},{"ty":"tm","s":{"a":0,"k":0,"ix":2},"e":{"a":0,"k":100,"ix":2},"o":{"a":0,"k":0,"ix":2},"m":1,"hd":false},{"ty":"tr","hd":false,"p":{"a":0,"k":[0,0],"ix":2},"a":{"a":0,"k":[0,0],"ix":2},"s":{"a":0,"k":[100,100],"ix":2},"r":{"a":0,"k":0,"ix":2},"o":{"a":0,"k":100,"ix":2},"sk":{"a":0,"k":0,"ix":2},"sa":{"a":0,"k":0,"ix":2}}]}],"ip":0,"op":526.6666666666666,"st":0,"bm":0}]},{"id":"11","layers":[{"ddd":0,"ind":34,"ty":4,"nm":"Mask 1 (Mask)","sr":1,"ks":{"o":{"a":0,"k":100,"ix":2},"r":{"a":0,"k":0,"ix":2},"p":{"a":0,"k":[10000,10000],"ix":2},"a":{"a":0,"k":[0,0],"ix":2},"s":{"a":0,"k":[100,100],"ix":2}},"td":1,"ao":0,"hd":false,"shapes":[{"ty":"gr","hd":false,"it":[{"ty":"sh","hd":false,"d":1,"ks":{"a":1,"k":[{"t":42,"s":[{"c":false,"v":[[114.817,36.647],[1.381,36.647],[1.32,36.478],[114.756,36.478],[114.817,36.647]],"i":[[0,0],[0,0],[0,0],[0,0],[0,0]],"o":[[0,0],[0,0],[0,0],[0,0],[0,0]]}],"i":{"x":[1],"y":[1]},"o":{"x":[0],"y":[0]}},{"t":75,"s":[{"c":false,"v":[[114.756,5.022],[1.32,5.022],[1.32,36.478],[114.756,36.478],[114.756,5.022]],"i":[[0,0],[0,0],[0,0],[0,0],[0,0]],"o":[[0,0],[0,0],[0,0],[0,0],[0,0]]}],"i":{"x":[1],"y":[1]},"o":{"x":[0],"y":[0]}}],"ix":2}},{"ty":"fl","c":{"a":0,"k":[0,0,0],"ix":2},"o":{"a":0,"k":100,"ix":2},"r":1,"bm":0,"nm":"Fill 1","mn":"ADBE Vector Graphic - Fill","hd":false},{"ty":"tm","s":{"a":0,"k":0,"ix":2},"e":{"a":0,"k":100,"ix":2},"o":{"a":0,"k":0,"ix":2},"m":1,"hd":false},{"ty":"tr","hd":false,"p":{"a":0,"k":[0,0],"ix":2},"a":{"a":0,"k":[0,0],"ix":2},"s":{"a":0,"k":[100,100],"ix":2},"r":{"a":0,"k":0,"ix":2},"o":{"a":0,"k":100,"ix":2},"sk":{"a":0,"k":0,"ix":2},"sa":{"a":0,"k":0,"ix":2}}]}],"ip":0,"op":526.6666666666666,"st":0,"bm":0},{"ddd":0,"refId":"10","w":20000,"h":20000,"ind":1,"ty":0,"nm":"papel bot Outlines (Masked Group)","sr":1,"ks":{"o":{"a":0,"k":100,"ix":2},"r":{"a":0,"k":0,"ix":2},"p":{"a":0,"k":[10000,10000],"ix":2},"a":{"a":0,"k":[10000,10000],"ix":2},"s":{"a":0,"k":[100,100],"ix":2}},"ao":0,"ip":0,"op":526.6666666666666,"st":0,"bm":0,"hd":false,"parent":0,"tt":1}]},{"id":"15","layers":[{"ddd":0,"refId":"14","w":20000,"h":20000,"ind":52,"ty":0,"nm":"Papel front Outlines (Masked Group)","sr":1,"ks":{"o":{"a":0,"k":100,"ix":2},"r":{"a":0,"k":0,"ix":2},"p":{"a":0,"k":[10042.09,10219.148],"ix":2},"a":{"a":0,"k":[10074.219,10089.605],"ix":2},"s":{"a":0,"k":[200,200],"ix":2}},"ao":0,"ip":0,"op":526.6666666666666,"st":0,"bm":0,"hd":false}]},{"id":"13","layers":[{"ddd":0,"ind":38,"ty":3,"nm":"","sr":1,"ks":{"o":{"a":0,"k":100,"ix":2},"r":{"a":0,"k":0,"ix":2},"p":{"a":0,"k":[10000,10000],"ix":2},"a":{"a":0,"k":[0,0],"ix":2},"s":{"a":0,"k":[100,100],"ix":2}},"ao":0,"ip":0,"op":526.6666666666666,"st":0,"bm":0,"hd":false},{"ddd":0,"ind":39,"ty":3,"nm":"","sr":1,"ks":{"o":{"a":0,"k":100,"ix":2},"r":{"a":0,"k":0,"ix":2},"p":{"a":0,"k":[0,0],"ix":2},"a":{"a":0,"k":[0,0],"ix":2},"s":{"a":0,"k":[100,100],"ix":2}},"ao":0,"ip":0,"op":526.6666666666666,"st":0,"bm":0,"hd":false,"parent":38},{"ddd":0,"ind":40,"ty":3,"nm":"","sr":1,"ks":{"o":{"a":0,"k":100,"ix":2},"r":{"a":0,"k":0,"ix":2},"p":{"a":0,"k":[0,0],"ix":2},"a":{"a":0,"k":[0,0],"ix":2},"s":{"a":0,"k":[100,100],"ix":2}},"ao":0,"ip":0,"op":526.6666666666666,"st":0,"bm":0,"hd":false,"parent":39},{"ddd":0,"ind":41,"ty":3,"nm":"","sr":1,"ks":{"o":{"a":0,"k":100,"ix":2},"r":{"a":0,"k":0,"ix":2},"p":{"a":0,"k":[0,0],"ix":2},"a":{"a":0,"k":[0,0],"ix":2},"s":{"a":0,"k":[100,100],"ix":2}},"ao":0,"ip":0,"op":526.6666666666666,"st":0,"bm":0,"hd":false,"parent":40},{"ddd":0,"ind":42,"ty":3,"nm":"","sr":1,"ks":{"o":{"a":0,"k":100,"ix":2},"r":{"a":0,"k":0,"ix":2},"p":{"a":0,"k":[0,0],"ix":2},"a":{"a":0,"k":[0,0],"ix":2},"s":{"a":0,"k":[100,100],"ix":2}},"ao":0,"ip":0,"op":526.6666666666666,"st":0,"bm":0,"hd":false,"parent":41},{"ddd":0,"ind":43,"ty":3,"nm":"","sr":1,"ks":{"o":{"a":0,"k":100,"ix":2},"r":{"a":0,"k":0,"ix":2},"p":{"a":0,"k":[71.074,92.141],"ix":2},"a":{"a":0,"k":[0,0],"ix":2},"s":{"a":0,"k":[100,100],"ix":2}},"ao":0,"ip":0,"op":526.6666666666666,"st":0,"bm":0,"hd":false,"parent":42},{"ddd":0,"ind":44,"ty":4,"nm":"Path","sr":1,"ks":{"o":{"a":0,"k":100,"ix":2},"r":{"a":0,"k":0,"ix":2},"p":{"a":0,"k":[0,0],"ix":2},"a":{"a":0,"k":[0,0],"ix":2},"s":{"a":0,"k":[100,100],"ix":2}},"ao":0,"hd":false,"parent":43,"shapes":[{"ty":"gr","hd":false,"it":[{"ty":"sh","hd":false,"d":1,"ks":{"a":0,"k":{"c":false,"v":[[68.364,-81.9],[67.331,-81.9],[51.208,-64.649],[51.208,-64.388],[51.208,57.931],[37.614,75.648],[34.951,75.996],[34.951,75.999],[34.882,75.999],[34.811,75.999],[-68.667,75.999],[-53.126,81.9],[-53.089,81.9],[-23.254,81.9],[33.132,81.9],[35.29,81.807],[38.48,81.268],[56.799,58.024],[56.799,-64.556],[56.799,-64.686],[67.385,-76.224],[68.667,-76.224],[68.364,-81.9]],"i":[[0,0],[0,0],[0.012,-9.145],[0,0],[0,0],[7.994,-2.106],[0.894,-0.009],[0,0],[0,0],[0,0],[0,0],[-5.953,-0.005],[0,0],[0,0],[0,0],[-0.61,0.093],[-1.049,0.26],[-0.014,11.099],[0,0],[0,0],[-5.937,0.544],[-0.326,-0.016],[0,0]],"o":[[0,0],[-9.048,0.551],[0,0],[0,0],[-0.017,8.335],[-0.874,0.227],[0,0],[0,0],[0,0],[0,0],[4.154,3.667],[0,0],[0,0],[0,0],[0.608,0],[1.075,-0.099],[10.716,-2.517],[0,0],[0,0],[0.079,-6.015],[0.328,-0.018],[0,0],[0,0]]}}},{"ty":"fl","c":{"a":0,"k":[0.9019607843137255,0.9019607843137255,0.9019607843137255],"ix":2},"o":{"a":0,"k":100,"ix":2},"r":1,"bm":0,"nm":"Fill 1","mn":"ADBE Vector Graphic - Fill","hd":false},{"ty":"tm","s":{"a":0,"k":0,"ix":2},"e":{"a":0,"k":100,"ix":2},"o":{"a":0,"k":0,"ix":2},"m":1,"hd":false},{"ty":"tr","hd":false,"p":{"a":0,"k":[0,0],"ix":2},"a":{"a":0,"k":[0,0],"ix":2},"s":{"a":0,"k":[100,100],"ix":2},"r":{"a":0,"k":0,"ix":2},"o":{"a":0,"k":100,"ix":2},"sk":{"a":0,"k":0,"ix":2},"sa":{"a":0,"k":0,"ix":2}}]}],"ip":0,"op":526.6666666666666,"st":0,"bm":0},{"ddd":0,"ind":45,"ty":3,"nm":"","sr":1,"ks":{"o":{"a":0,"k":100,"ix":2},"r":{"a":0,"k":0,"ix":2},"p":{"a":0,"k":[74.219,91.151],"ix":2},"a":{"a":0,"k":[0,0],"ix":2},"s":{"a":0,"k":[100,100],"ix":2}},"ao":0,"ip":0,"op":526.6666666666666,"st":0,"bm":0,"hd":false,"parent":41},{"ddd":0,"ind":46,"ty":4,"nm":"Group","sr":1,"ks":{"o":{"a":0,"k":100,"ix":2},"r":{"a":0,"k":0,"ix":2},"p":{"a":0,"k":[0,0],"ix":2},"a":{"a":0,"k":[0,0],"ix":2},"s":{"a":0,"k":[100,100],"ix":2}},"ao":0,"hd":false,"parent":45,"shapes":[{"ty":"gr","hd":false,"it":[{"ty":"gr","hd":false,"it":[{"ty":"gr","hd":false,"it":[{"ty":"sh","hd":false,"d":1,"ks":{"a":0,"k":{"c":false,"v":[[-57.614,-15.262],[-57.614,-11.587]],"i":[[0,0],[0,0]],"o":[[0,0],[0,0]]}}},{"ty":"tm","s":{"a":0,"k":0,"ix":2},"e":{"a":0,"k":100,"ix":2},"o":{"a":0,"k":0,"ix":2},"m":1,"hd":false},{"ty":"tr","hd":false,"p":{"a":0,"k":[0,0],"ix":2},"a":{"a":0,"k":[0,0],"ix":2},"s":{"a":0,"k":[100,100],"ix":2},"r":{"a":0,"k":0,"ix":2},"o":{"a":0,"k":100,"ix":2},"sk":{"a":0,"k":0,"ix":2},"sa":{"a":0,"k":0,"ix":2}}]},{"ty":"gr","hd":false,"it":[{"ty":"sh","hd":false,"d":1,"ks":{"a":0,"k":{"c":false,"v":[[-65.219,79.059],[-58.189,68.737],[-58.135,4.655]],"i":[[0,0],[0,3.997],[0,8.289]],"o":[[5.953,0],[0,-32.687],[0,0]]}}},{"ty":"tm","s":{"a":0,"k":0,"ix":2},"e":{"a":0,"k":100,"ix":2},"o":{"a":0,"k":0,"ix":2},"m":1,"hd":false},{"ty":"tr","hd":false,"p":{"a":0,"k":[0,0],"ix":2},"a":{"a":0,"k":[0,0],"ix":2},"s":{"a":0,"k":[100,100],"ix":2},"r":{"a":0,"k":0,"ix":2},"o":{"a":0,"k":100,"ix":2},"sk":{"a":0,"k":0,"ix":2},"sa":{"a":0,"k":0,"ix":2}}]},{"ty":"tr","hd":false,"p":{"a":0,"k":[0,0],"ix":2},"a":{"a":0,"k":[0,0],"ix":2},"s":{"a":0,"k":[100,100],"ix":2},"r":{"a":0,"k":0,"ix":2},"o":{"a":0,"k":100,"ix":2},"sk":{"a":0,"k":0,"ix":2},"sa":{"a":0,"k":0,"ix":2}}]},{"ty":"gr","hd":false,"it":[{"ty":"sh","hd":false,"d":1,"ks":{"a":0,"k":{"c":false,"v":[[-58.135,-24.607],[-58.135,-55.195],[-34.467,-79.059],[65.219,-79.059]],"i":[[0,0],[0,0],[-13.063,0.021],[0,0]],"o":[[0,0],[0.021,-13.171],[0,0],[0,0]]}}},{"ty":"tm","s":{"a":0,"k":0,"ix":2},"e":{"a":0,"k":100,"ix":2},"o":{"a":0,"k":0,"ix":2},"m":1,"hd":false},{"ty":"tr","hd":false,"p":{"a":0,"k":[0,0],"ix":2},"a":{"a":0,"k":[0,0],"ix":2},"s":{"a":0,"k":[100,100],"ix":2},"r":{"a":0,"k":0,"ix":2},"o":{"a":0,"k":100,"ix":2},"sk":{"a":0,"k":0,"ix":2},"sa":{"a":0,"k":0,"ix":2}}]},{"ty":"st","c":{"a":0,"k":[0.9019607843137255,0.9019607843137255,0.9019607843137255],"ix":2},"o":{"a":0,"k":100,"ix":2},"w":{"a":0,"k":3.6,"ix":2},"hd":false,"lc":2,"lj":2},{"ty":"tr","hd":false,"p":{"a":0,"k":[0,0],"ix":2},"a":{"a":0,"k":[0,0],"ix":2},"s":{"a":0,"k":[100,100],"ix":2},"r":{"a":0,"k":0,"ix":2},"o":{"a":0,"k":100,"ix":2},"sk":{"a":0,"k":0,"ix":2},"sa":{"a":0,"k":0,"ix":2}}]}],"ip":0,"op":526.6666666666666,"st":0,"bm":0},{"ddd":0,"ind":47,"ty":3,"nm":"","sr":1,"ks":{"o":{"a":0,"k":100,"ix":2},"r":{"a":0,"k":0,"ix":2},"p":{"a":0,"k":[45.83,62.33],"ix":2},"a":{"a":0,"k":[0,0],"ix":2},"s":{"a":0,"k":[100,100],"ix":2}},"ao":0,"ip":0,"op":526.6666666666666,"st":0,"bm":0,"hd":false,"parent":40},{"ddd":0,"ind":48,"ty":4,"nm":"Path","sr":1,"ks":{"o":{"a":0,"k":100,"ix":2},"r":{"a":0,"k":0,"ix":2},"p":{"a":0,"k":[0,0],"ix":2},"a":{"a":0,"k":[0,0],"ix":2},"s":{"a":0,"k":[100,100],"ix":2}},"ao":0,"hd":false,"parent":47,"shapes":[{"ty":"gr","hd":false,"it":[{"ty":"sh","hd":false,"d":1,"ks":{"a":0,"k":{"c":false,"v":[[-6.133,-52.006],[-29.801,-28.142],[-29.801,52.08],[29.801,-52.08],[-6.133,-52.006]],"i":[[0,0],[0.02,-13.17],[0,0],[0,0],[0,0]],"o":[[-13.063,0.021],[0,0],[0,0],[0,0],[-13.063,0.021]]}}},{"ty":"fl","c":{"a":0,"k":[0.9411764705882353,0.9411764705882353,0.9411764705882353],"ix":2},"o":{"a":0,"k":100,"ix":2},"r":1,"bm":0,"nm":"Fill 1","mn":"ADBE Vector Graphic - Fill","hd":false},{"ty":"tm","s":{"a":0,"k":0,"ix":2},"e":{"a":0,"k":100,"ix":2},"o":{"a":0,"k":0,"ix":2},"m":1,"hd":false},{"ty":"tr","hd":false,"p":{"a":0,"k":[0,0],"ix":2},"a":{"a":0,"k":[0,0],"ix":2},"s":{"a":0,"k":[100,100],"ix":2},"r":{"a":0,"k":0,"ix":2},"o":{"a":0,"k":100,"ix":2},"sk":{"a":0,"k":0,"ix":2},"sa":{"a":0,"k":0,"ix":2}}]}],"ip":0,"op":526.6666666666666,"st":0,"bm":0},{"ddd":0,"ind":49,"ty":3,"nm":"","sr":1,"ks":{"o":{"a":0,"k":100,"ix":2},"r":{"a":0,"k":0,"ix":2},"p":{"a":0,"k":[77.799,92.164],"ix":2},"a":{"a":0,"k":[0,0],"ix":2},"s":{"a":0,"k":[100,100],"ix":2}},"ao":0,"ip":0,"op":526.6666666666666,"st":0,"bm":0,"hd":false,"parent":39},{"ddd":0,"ind":50,"ty":4,"nm":"Path","sr":1,"ks":{"o":{"a":0,"k":100,"ix":2},"r":{"a":0,"k":0,"ix":2},"p":{"a":0,"k":[0,0],"ix":2},"a":{"a":0,"k":[0,0],"ix":2},"s":{"a":0,"k":[100,100],"ix":2}},"ao":0,"hd":false,"parent":49,"shapes":[{"ty":"gr","hd":false,"it":[{"ty":"sh","hd":false,"d":1,"ks":{"a":0,"k":{"c":false,"v":[[61.639,-76.59],[61.639,-81.84],[-38.048,-81.84],[-61.714,-57.977],[-61.714,79.05],[-58.947,81.84],[26.406,81.84],[50.018,57.977],[50.018,-64.542],[50.018,-64.673],[61.639,-76.581],[61.714,-76.59],[61.639,-76.59]],"i":[[0,0],[0,0],[0,0],[0.02,-13.17],[0,0],[-1.527,0],[0,0],[-0.009,13.153],[0,0],[0,0],[-6.363,0.009],[-0.025,0.001],[0,0]],"o":[[0,0],[0,0],[-13.062,0.02],[0,0],[0,1.54],[0,0],[13.045,-0.041],[0,0],[0,0],[0.081,-6.417],[0.026,0],[0,0],[0,0]]}}},{"ty":"fl","c":{"a":0,"k":[1,1,1],"ix":2},"o":{"a":0,"k":100,"ix":2},"r":1,"bm":0,"nm":"Fill 1","mn":"ADBE Vector Graphic - Fill","hd":false},{"ty":"tm","s":{"a":0,"k":0,"ix":2},"e":{"a":0,"k":100,"ix":2},"o":{"a":0,"k":0,"ix":2},"m":1,"hd":false},{"ty":"tr","hd":false,"p":{"a":0,"k":[0,0],"ix":2},"a":{"a":0,"k":[0,0],"ix":2},"s":{"a":0,"k":[100,100],"ix":2},"r":{"a":0,"k":0,"ix":2},"o":{"a":0,"k":100,"ix":2},"sk":{"a":0,"k":0,"ix":2},"sa":{"a":0,"k":0,"ix":2}}]}],"ip":0,"op":526.6666666666666,"st":0,"bm":0}]},{"id":"14","layers":[{"ddd":0,"ind":51,"ty":4,"nm":"Mask 1 (Mask)","sr":1,"ks":{"o":{"a":0,"k":100,"ix":2},"r":{"a":0,"k":0,"ix":2},"p":{"a":0,"k":[10000,10000],"ix":2},"a":{"a":0,"k":[0,0],"ix":2},"s":{"a":0,"k":[100,100],"ix":2}},"td":1,"ao":0,"hd":false,"shapes":[{"ty":"gr","hd":false,"it":[{"ty":"sh","hd":false,"d":1,"ks":{"a":1,"k":[{"t":17,"s":[{"c":false,"v":[[152.276,7.781],[-1.326,7.781],[-1.326,9.031],[152.276,9.031],[152.276,7.781]],"i":[[0,0],[0,0],[0,0],[0,0],[0,0]],"o":[[0,0],[0,0],[0,0],[0,0],[0,0]]}],"i":{"x":[1],"y":[1]},"o":{"x":[0],"y":[0]}},{"t":42,"s":[{"c":false,"v":[[152.276,7.781],[-1.326,7.781],[-1.326,175.031],[152.276,175.031],[152.276,7.781]],"i":[[0,0],[0,0],[0,0],[0,0],[0,0]],"o":[[0,0],[0,0],[0,0],[0,0],[0,0]]}],"i":{"x":[1],"y":[1]},"o":{"x":[0],"y":[0]}}],"ix":2}},{"ty":"fl","c":{"a":0,"k":[0,0,0],"ix":2},"o":{"a":0,"k":100,"ix":2},"r":1,"bm":0,"nm":"Fill 1","mn":"ADBE Vector Graphic - Fill","hd":false},{"ty":"tm","s":{"a":0,"k":0,"ix":2},"e":{"a":0,"k":100,"ix":2},"o":{"a":0,"k":0,"ix":2},"m":1,"hd":false},{"ty":"tr","hd":false,"p":{"a":0,"k":[0,0],"ix":2},"a":{"a":0,"k":[0,0],"ix":2},"s":{"a":0,"k":[100,100],"ix":2},"r":{"a":0,"k":0,"ix":2},"o":{"a":0,"k":100,"ix":2},"sk":{"a":0,"k":0,"ix":2},"sa":{"a":0,"k":0,"ix":2}}]}],"ip":0,"op":526.6666666666666,"st":0,"bm":0},{"ddd":0,"refId":"13","w":20000,"h":20000,"ind":1,"ty":0,"nm":"Papel front Outlines (Masked Group)","sr":1,"ks":{"o":{"a":0,"k":100,"ix":2},"r":{"a":0,"k":0,"ix":2},"p":{"a":0,"k":[10000,10000],"ix":2},"a":{"a":0,"k":[10000,10000],"ix":2},"s":{"a":0,"k":[100,100],"ix":2}},"ao":0,"ip":0,"op":526.6666666666666,"st":0,"bm":0,"hd":false,"parent":0,"tt":1}]},{"id":"16","layers":[{"ddd":0,"ind":54,"ty":3,"nm":"","sr":1,"ks":{"o":{"a":0,"k":100,"ix":2},"r":{"a":0,"k":0,"ix":2},"p":{"a":0,"k":[10000,10000],"ix":2},"a":{"a":0,"k":[0,0],"ix":2},"s":{"a":0,"k":[100,100],"ix":2}},"ao":0,"ip":0,"op":526.6666666666666,"st":0,"bm":0,"hd":false},{"ddd":0,"ind":55,"ty":3,"nm":"","sr":1,"ks":{"o":{"a":0,"k":100,"ix":2},"r":{"a":0,"k":0,"ix":2},"p":{"a":0,"k":[0,0],"ix":2},"a":{"a":0,"k":[0,0],"ix":2},"s":{"a":0,"k":[100,100],"ix":2}},"ao":0,"ip":0,"op":526.6666666666666,"st":0,"bm":0,"hd":false,"parent":54},{"ddd":0,"ind":56,"ty":3,"nm":"","sr":1,"ks":{"o":{"a":0,"k":100,"ix":2},"r":{"a":0,"k":0,"ix":2},"p":{"a":0,"k":[0,0],"ix":2},"a":{"a":0,"k":[0,0],"ix":2},"s":{"a":0,"k":[100,100],"ix":2}},"ao":0,"ip":0,"op":526.6666666666666,"st":0,"bm":0,"hd":false,"parent":55},{"ddd":0,"ind":57,"ty":3,"nm":"","sr":1,"ks":{"o":{"a":0,"k":100,"ix":2},"r":{"a":0,"k":0,"ix":2},"p":{"a":0,"k":[69.205,25.502],"ix":2},"a":{"a":0,"k":[0,0],"ix":2},"s":{"a":0,"k":[100,100],"ix":2}},"ao":0,"ip":0,"op":526.6666666666666,"st":0,"bm":0,"hd":false,"parent":56},{"ddd":0,"ind":58,"ty":4,"nm":"Path","sr":1,"ks":{"o":{"a":0,"k":100,"ix":2},"r":{"a":0,"k":0,"ix":2},"p":{"a":0,"k":[0,0],"ix":2},"a":{"a":0,"k":[0,0],"ix":2},"s":{"a":0,"k":[100,100],"ix":2}},"ao":0,"hd":false,"parent":57,"shapes":[{"ty":"gr","hd":false,"it":[{"ty":"sh","hd":false,"d":1,"ks":{"a":0,"k":{"c":false,"v":[[-58.955,-12.455],[-56.155,-9.658],[41.758,-9.658],[53.379,2.066],[53.379,15.334],[56.147,15.334],[58.914,12.543],[58.914,2.066],[41.814,-15.334],[41.703,-15.334],[40.67,-15.334],[39.918,-15.251],[-56.159,-15.251],[-58.955,-12.455]],"i":[[0,-1.544],[-1.545,0],[-0.018,-0.001],[-0.01,-6.471],[0,0],[0,0],[0,1.541],[0,0],[9.485,0.041],[0,0],[0,0],[0.251,-0.027],[0,0],[0,-1.544]],"o":[[0,1.544],[97.877,0],[6.414,0.011],[0,0],[0,0],[1.527,0],[0,0],[0.041,-9.569],[0,0],[0,0],[-0.254,0.015],[0,0],[-1.544,0],[0,1.544]]}}},{"ty":"fl","c":{"a":0,"k":[0.9019607843137255,0.9019607843137255,0.9019607843137255],"ix":2},"o":{"a":0,"k":100,"ix":2},"r":1,"bm":0,"nm":"Fill 1","mn":"ADBE Vector Graphic - Fill","hd":false},{"ty":"tm","s":{"a":0,"k":0,"ix":2},"e":{"a":0,"k":100,"ix":2},"o":{"a":0,"k":0,"ix":2},"m":1,"hd":false},{"ty":"tr","hd":false,"p":{"a":0,"k":[0,0],"ix":2},"a":{"a":0,"k":[0,0],"ix":2},"s":{"a":0,"k":[100,100],"ix":2},"r":{"a":0,"k":0,"ix":2},"o":{"a":0,"k":100,"ix":2},"sk":{"a":0,"k":0,"ix":2},"sa":{"a":0,"k":0,"ix":2}}]}],"ip":0,"op":526.6666666666666,"st":0,"bm":0},{"ddd":0,"ind":59,"ty":3,"nm":"","sr":1,"ks":{"o":{"a":0,"k":100,"ix":2},"r":{"a":0,"k":0,"ix":2},"p":{"a":0,"k":[68.824,26.86],"ix":2},"a":{"a":0,"k":[0,0],"ix":2},"s":{"a":0,"k":[100,100],"ix":2}},"ao":0,"ip":0,"op":526.6666666666666,"st":0,"bm":0,"hd":false,"parent":55},{"ddd":0,"ind":60,"ty":4,"nm":"Path","sr":1,"ks":{"o":{"a":0,"k":100,"ix":2},"r":{"a":0,"k":0,"ix":2},"p":{"a":0,"k":[0,0],"ix":2},"a":{"a":0,"k":[0,0],"ix":2},"s":{"a":0,"k":[100,100],"ix":2}},"ao":0,"hd":false,"parent":59,"shapes":[{"ty":"gr","hd":false,"it":[{"ty":"sh","hd":false,"d":1,"ks":{"a":0,"k":{"c":false,"v":[[-58.571,-15.544],[-40.571,3.353],[-40.571,13.652],[-37.803,16.61],[56.472,15.79],[59.24,12.833],[59.24,1.73],[42.083,-16.61],[-58.571,-15.544]],"i":[[-0.67,0],[0,-9.44],[0,0],[-1.527,0],[0,0],[0,1.632],[0,0],[9.475,0],[-0.67,0]],"o":[[16,0],[0,0],[0,1.632],[0,0],[1.528,0],[0,0],[0,-10.128],[-0.642,0],[16,0]]}}},{"ty":"fl","c":{"a":0,"k":[0.9019607843137255,0.9019607843137255,0.9019607843137255],"ix":2},"o":{"a":0,"k":100,"ix":2},"r":1,"bm":0,"nm":"Fill 1","mn":"ADBE Vector Graphic - Fill","hd":false},{"ty":"tm","s":{"a":0,"k":0,"ix":2},"e":{"a":0,"k":100,"ix":2},"o":{"a":0,"k":0,"ix":2},"m":1,"hd":false},{"ty":"tr","hd":false,"p":{"a":0,"k":[0,0],"ix":2},"a":{"a":0,"k":[0,0],"ix":2},"s":{"a":0,"k":[100,100],"ix":2},"r":{"a":0,"k":0,"ix":2},"o":{"a":0,"k":100,"ix":2},"sk":{"a":0,"k":0,"ix":2},"sa":{"a":0,"k":0,"ix":2}}]}],"ip":0,"op":526.6666666666666,"st":0,"bm":0}]},{"id":"17","layers":[{"ddd":0,"ind":61,"ty":4,"nm":"Mask 1 (Mask)","sr":1,"ks":{"o":{"a":0,"k":100,"ix":2},"r":{"a":0,"k":0,"ix":2},"p":{"a":0,"k":[10000,10000],"ix":2},"a":{"a":0,"k":[0,0],"ix":2},"s":{"a":0,"k":[100,100],"ix":2}},"td":1,"ao":0,"hd":false,"shapes":[{"ty":"gr","hd":false,"it":[{"ty":"sh","hd":false,"d":1,"ks":{"a":1,"k":[{"t":0,"s":[{"c":false,"v":[[133.251,43.755],[8.394,43.755],[8.394,45.207],[133.251,45.207],[133.251,43.755]],"i":[[0,0],[0,0],[0,0],[0,0],[0,0]],"o":[[0,0],[0,0],[0,0],[0,0],[0,0]]}],"i":{"x":[1],"y":[1]},"o":{"x":[0],"y":[0]}},{"t":17,"s":[{"c":false,"v":[[133.324,9.505],[8.466,9.505],[8.394,45.207],[133.251,45.207],[133.324,9.505]],"i":[[0,0],[0,0],[0,0],[0,0],[0,0]],"o":[[0,0],[0,0],[0,0],[0,0],[0,0]]}],"i":{"x":[1],"y":[1]},"o":{"x":[0],"y":[0]}}],"ix":2}},{"ty":"fl","c":{"a":0,"k":[0,0,0],"ix":2},"o":{"a":0,"k":100,"ix":2},"r":1,"bm":0,"nm":"Fill 1","mn":"ADBE Vector Graphic - Fill","hd":false},{"ty":"tm","s":{"a":0,"k":0,"ix":2},"e":{"a":0,"k":100,"ix":2},"o":{"a":0,"k":0,"ix":2},"m":1,"hd":false},{"ty":"tr","hd":false,"p":{"a":0,"k":[0,0],"ix":2},"a":{"a":0,"k":[0,0],"ix":2},"s":{"a":0,"k":[100,100],"ix":2},"r":{"a":0,"k":0,"ix":2},"o":{"a":0,"k":100,"ix":2},"sk":{"a":0,"k":0,"ix":2},"sa":{"a":0,"k":0,"ix":2}}]}],"ip":0,"op":526.6666666666666,"st":0,"bm":0},{"ddd":0,"refId":"16","w":20000,"h":20000,"ind":1,"ty":0,"nm":"Papel top Outlines (Masked Group)","sr":1,"ks":{"o":{"a":0,"k":100,"ix":2},"r":{"a":0,"k":0,"ix":2},"p":{"a":0,"k":[10000,10000],"ix":2},"a":{"a":0,"k":[10000,10000],"ix":2},"s":{"a":0,"k":[100,100],"ix":2}},"ao":0,"ip":0,"op":526.6666666666666,"st":0,"bm":0,"hd":false,"parent":0,"tt":1}]},{"id":"18","layers":[{"ddd":0,"ind":63,"ty":3,"nm":"","sr":1,"ks":{"o":{"a":0,"k":100,"ix":2},"r":{"a":0,"k":0,"ix":2},"p":{"a":0,"k":[10516.83,10232.086],"ix":2},"a":{"a":0,"k":[7.194,7.198],"ix":2},"s":{"a":1,"k":[{"t":387,"s":[0,0],"i":{"x":[1],"y":[1]},"o":{"x":[0],"y":[0]}},{"t":420,"s":[240,240],"i":{"x":[1],"y":[1]},"o":{"x":[0],"y":[0]}},{"t":473,"s":[200,200],"i":{"x":[1],"y":[1]},"o":{"x":[0],"y":[0]}}],"ix":2}},"ao":0,"ip":0,"op":526.6666666666666,"st":0,"bm":0,"hd":false},{"ddd":0,"ind":64,"ty":4,"nm":"Group 1","sr":1,"ks":{"o":{"a":0,"k":100,"ix":2},"r":{"a":0,"k":0,"ix":2},"p":{"a":0,"k":[0,0],"ix":2},"a":{"a":0,"k":[0,0],"ix":2},"s":{"a":0,"k":[100,100],"ix":2}},"ao":0,"hd":false,"parent":63,"shapes":[{"ty":"gr","hd":false,"it":[{"ty":"gr","hd":false,"it":[{"ty":"sh","hd":false,"d":1,"ks":{"a":0,"k":{"c":false,"v":[[0,2.988],[2.976,0],[0,-2.988],[-2.977,0],[0,2.988]],"i":[[-1.643,0],[0,1.652],[1.642,0],[0,-1.652],[-1.643,0]],"o":[[1.642,0],[0,-1.652],[-1.643,0],[0,1.652],[1.642,0]]}}},{"ty":"tm","s":{"a":0,"k":0,"ix":2},"e":{"a":0,"k":100,"ix":2},"o":{"a":0,"k":0,"ix":2},"m":1,"hd":false},{"ty":"tr","hd":false,"p":{"a":0,"k":[0,0],"ix":2},"a":{"a":0,"k":[0,0],"ix":2},"s":{"a":0,"k":[100,100],"ix":2},"r":{"a":0,"k":0,"ix":2},"o":{"a":0,"k":100,"ix":2},"sk":{"a":0,"k":0,"ix":2},"sa":{"a":0,"k":0,"ix":2}}]},{"ty":"gr","hd":false,"it":[{"ty":"sh","hd":false,"d":1,"ks":{"a":0,"k":{"c":false,"v":[[0,6.948],[-6.944,0],[0,-6.948],[6.944,0],[0,6.948]],"i":[[3.837,0],[0,3.836],[-3.837,0],[0,-3.836],[3.837,0]],"o":[[-3.837,0],[0,-3.836],[3.837,0],[0,3.836],[-3.837,0]]}}},{"ty":"tm","s":{"a":0,"k":0,"ix":2},"e":{"a":0,"k":100,"ix":2},"o":{"a":0,"k":0,"ix":2},"m":1,"hd":false},{"ty":"tr","hd":false,"p":{"a":0,"k":[0,0],"ix":2},"a":{"a":0,"k":[0,0],"ix":2},"s":{"a":0,"k":[100,100],"ix":2},"r":{"a":0,"k":0,"ix":2},"o":{"a":0,"k":100,"ix":2},"sk":{"a":0,"k":0,"ix":2},"sa":{"a":0,"k":0,"ix":2}}]},{"ty":"fl","c":{"a":0,"k":[0.9019607843137255,0.9019607843137255,0.9019607843137255],"ix":2},"o":{"a":0,"k":100,"ix":2},"r":1,"bm":0,"nm":"Fill 1","mn":"ADBE Vector Graphic - Fill","hd":false},{"ty":"tr","hd":false,"p":{"a":0,"k":[7.193999767303467,7.197999954223633],"ix":2},"a":{"a":0,"k":[0,0],"ix":2},"s":{"a":0,"k":[100,100],"ix":2},"r":{"a":0,"k":0,"ix":2},"o":{"a":0,"k":100,"ix":2},"sk":{"a":0,"k":0,"ix":2},"sa":{"a":0,"k":0,"ix":2}}]}],"ip":0,"op":526.6666666666666,"st":0,"bm":0}]},{"id":"19","layers":[{"ddd":0,"ind":66,"ty":3,"nm":"","sr":1,"ks":{"o":{"a":0,"k":100,"ix":2},"r":{"a":0,"k":0,"ix":2},"p":{"a":0,"k":[10096.613,10416.097],"ix":2},"a":{"a":0,"k":[6.515,6.515],"ix":2},"s":{"a":1,"k":[{"t":420,"s":[0,0],"i":{"x":[1],"y":[1]},"o":{"x":[0],"y":[0]}},{"t":453,"s":[240,240],"i":{"x":[1],"y":[1]},"o":{"x":[0],"y":[0]}},{"t":507,"s":[200,200],"i":{"x":[1],"y":[1]},"o":{"x":[0],"y":[0]}}],"ix":2}},"ao":0,"ip":0,"op":526.6666666666666,"st":0,"bm":0,"hd":false},{"ddd":0,"ind":67,"ty":4,"nm":"Group 1","sr":1,"ks":{"o":{"a":0,"k":100,"ix":2},"r":{"a":0,"k":0,"ix":2},"p":{"a":0,"k":[0,0],"ix":2},"a":{"a":0,"k":[0,0],"ix":2},"s":{"a":0,"k":[100,100],"ix":2}},"ao":0,"hd":false,"parent":66,"shapes":[{"ty":"gr","hd":false,"it":[{"ty":"sh","hd":false,"d":1,"ks":{"a":0,"k":{"c":false,"v":[[6.258,3.885],[3.885,6.258],[0.001,2.372],[-3.891,6.264],[-6.264,3.891],[-2.374,-0.001],[-6.258,-3.885],[-3.885,-6.26],[-0.001,-2.374],[3.891,-6.264],[6.264,-3.891],[2.374,0.001],[6.258,3.885]],"i":[[0,0],[0,0],[0,0],[0,0],[0,0],[0,0],[0,0],[0,0],[0,0],[0,0],[0,0],[0,0],[0,0]],"o":[[0,0],[0,0],[0,0],[0,0],[0,0],[0,0],[0,0],[0,0],[0,0],[0,0],[0,0],[0,0],[0,0]]}}},{"ty":"fl","c":{"a":0,"k":[0.9019607843137255,0.9019607843137255,0.9019607843137255],"ix":2},"o":{"a":0,"k":100,"ix":2},"r":1,"bm":0,"nm":"Fill 1","mn":"ADBE Vector Graphic - Fill","hd":false},{"ty":"tm","s":{"a":0,"k":0,"ix":2},"e":{"a":0,"k":100,"ix":2},"o":{"a":0,"k":0,"ix":2},"m":1,"hd":false},{"ty":"tr","hd":false,"p":{"a":0,"k":[6.514999866485596,6.514999866485596],"ix":2},"a":{"a":0,"k":[0,0],"ix":2},"s":{"a":0,"k":[100,100],"ix":2},"r":{"a":0,"k":0,"ix":2},"o":{"a":0,"k":100,"ix":2},"sk":{"a":0,"k":0,"ix":2},"sa":{"a":0,"k":0,"ix":2}}]}],"ip":0,"op":526.6666666666666,"st":0,"bm":0}]},{"id":"20","layers":[{"ddd":0,"ind":69,"ty":4,"nm":"Group 1","sr":1,"ks":{"o":{"a":0,"k":100,"ix":2},"r":{"a":0,"k":0,"ix":2},"p":{"a":0,"k":[10000,10000],"ix":2},"a":{"a":0,"k":[0,0],"ix":2},"s":{"a":0,"k":[100,100],"ix":2}},"ao":0,"hd":false,"shapes":[{"ty":"gr","hd":false,"it":[{"ty":"sh","hd":false,"d":1,"ks":{"a":0,"k":{"c":false,"v":[[-7.063,94.323],[115.603,35.774],[39.645,-45.798],[7.22,-76.517],[-84.949,-76.912],[-94.997,22.24],[-7.063,94.323]],"i":[[-34.357,-7.157],[-2.441,47.062],[17.957,18.605],[34.584,38.554],[38.389,-25.44],[-24.266,-40.899],[-34.357,-7.157]],"o":[[79.337,8.029],[3.66,-70.593],[-17.958,-18.605],[-23.057,-25.703],[-30.965,25.202],[24.266,40.898],[79.337,8.029]]}}},{"ty":"fl","c":{"a":0,"k":[0.7137254901960784,0.9411764705882353,0.611764705882353],"ix":2},"o":{"a":0,"k":53.250444613821145,"ix":2},"r":1,"bm":0,"nm":"Fill 1","mn":"ADBE Vector Graphic - Fill","hd":false},{"ty":"tm","s":{"a":0,"k":0,"ix":2},"e":{"a":0,"k":100,"ix":2},"o":{"a":0,"k":0,"ix":2},"m":1,"hd":false},{"ty":"tr","hd":false,"p":{"a":0,"k":[119.5130004882812,102.6019973754883],"ix":2},"a":{"a":0,"k":[0,0],"ix":2},"s":{"a":0,"k":[100,100],"ix":2},"r":{"a":0,"k":0,"ix":2},"o":{"a":0,"k":100,"ix":2},"sk":{"a":0,"k":0,"ix":2},"sa":{"a":0,"k":0,"ix":2}}]}],"ip":0,"op":526.6666666666666,"st":0,"bm":0}]}],"layers":[{"ddd":0,"ind":1,"ty":3,"nm":"","sr":1,"ks":{"o":{"a":0,"k":100,"ix":2},"r":{"a":1,"k":[{"t":57,"s":[64],"i":{"x":[1],"y":[1]},"o":{"x":[0],"y":[0]}},{"t":153,"s":[23],"i":{"x":[1],"y":[1]},"o":{"x":[0],"y":[0]}},{"t":222,"s":[-21],"i":{"x":[1],"y":[1]},"o":{"x":[0],"y":[0]}},{"t":305,"s":[16],"i":{"x":[1],"y":[1]},"o":{"x":[0],"y":[0]}},{"t":367,"s":[0],"i":{"x":[1],"y":[1]},"o":{"x":[0],"y":[0]}}],"ix":2},"p":{"a":1,"k":[{"t":57,"s":[240.252,377.045],"i":{"x":[1],"y":[1]},"o":{"x":[0],"y":[0]}},{"t":147,"s":[323.752,265.045],"i":{"x":[1],"y":[1]},"o":{"x":[0],"y":[0]}},{"t":222,"s":[334.252,403.045],"i":{"x":[1],"y":[1]},"o":{"x":[0],"y":[0]}},{"t":305,"s":[499.252,415.045],"i":{"x":[1],"y":[1]},"o":{"x":[0],"y":[0]}}],"ix":2},"a":{"a":0,"k":[47.206,48.054],"ix":2},"s":{"a":1,"k":[{"t":57,"s":[0,0],"i":{"x":[1],"y":[1]},"o":{"x":[0],"y":[0]}},{"t":100,"s":[240,240],"i":{"x":[1],"y":[1]},"o":{"x":[0],"y":[0]}},{"t":222,"s":[240,240],"i":{"x":[1],"y":[1]},"o":{"x":[0],"y":[0]}},{"t":305,"s":[400,400],"i":{"x":[1],"y":[1]},"o":{"x":[0],"y":[0]}}],"ix":2}},"ao":0,"ip":0,"op":526.6666666666666,"st":0,"bm":0,"hd":false},{"ddd":0,"refId":"1","w":20000,"h":20000,"ind":6,"ty":0,"nm":"LUPA rotacion 3D (In/Out)","sr":1,"ks":{"o":{"a":1,"k":[{"t":56,"s":[0],"i":{"x":[1],"y":[1]},"o":{"x":[0],"y":[0]}},{"t":57,"s":[100],"i":{"x":[1],"y":[1]},"o":{"x":[0],"y":[0]}},{"t":701,"s":[100],"i":{"x":[1],"y":[1]},"o":{"x":[0],"y":[0]}},{"t":702,"s":[0],"i":{"x":[1],"y":[1]},"o":{"x":[0],"y":[0]}}],"ix":2},"r":{"a":0,"k":0,"ix":2},"p":{"a":0,"k":[0,0],"ix":2},"a":{"a":0,"k":[10000,10000],"ix":2},"s":{"a":0,"k":[100,100],"ix":2}},"ao":0,"ip":0,"op":526.6666666666666,"st":0,"bm":0,"hd":false,"parent":1},{"ddd":0,"refId":"2","w":20000,"h":20000,"ind":8,"ty":0,"nm":"line 1 Outlines (In/Out)","sr":1,"ks":{"o":{"a":1,"k":[{"t":27,"s":[0],"i":{"x":[1],"y":[1]},"o":{"x":[0],"y":[0]}},{"t":28,"s":[100],"i":{"x":[1],"y":[1]},"o":{"x":[0],"y":[0]}},{"t":701,"s":[100],"i":{"x":[1],"y":[1]},"o":{"x":[0],"y":[0]}},{"t":702,"s":[0],"i":{"x":[1],"y":[1]},"o":{"x":[0],"y":[0]}}],"ix":2},"r":{"a":0,"k":0,"ix":2},"p":{"a":0,"k":[0,0],"ix":2},"a":{"a":0,"k":[10000,10000],"ix":2},"s":{"a":0,"k":[100,100],"ix":2}},"ao":0,"ip":0,"op":526.6666666666666,"st":0,"bm":0,"hd":false},{"ddd":0,"refId":"3","w":20000,"h":20000,"ind":10,"ty":0,"nm":"line 2 Outlines (In/Out)","sr":1,"ks":{"o":{"a":1,"k":[{"t":39,"s":[0],"i":{"x":[1],"y":[1]},"o":{"x":[0],"y":[0]}},{"t":40,"s":[100],"i":{"x":[1],"y":[1]},"o":{"x":[0],"y":[0]}},{"t":712,"s":[100],"i":{"x":[1],"y":[1]},"o":{"x":[0],"y":[0]}},{"t":713,"s":[0],"i":{"x":[1],"y":[1]},"o":{"x":[0],"y":[0]}}],"ix":2},"r":{"a":0,"k":0,"ix":2},"p":{"a":0,"k":[0,0],"ix":2},"a":{"a":0,"k":[10000,10000],"ix":2},"s":{"a":0,"k":[100,100],"ix":2}},"ao":0,"ip":0,"op":526.6666666666666,"st":0,"bm":0,"hd":false},{"ddd":0,"refId":"4","w":20000,"h":20000,"ind":12,"ty":0,"nm":"line 3 Outlines (In/Out)","sr":1,"ks":{"o":{"a":1,"k":[{"t":51,"s":[0],"i":{"x":[1],"y":[1]},"o":{"x":[0],"y":[0]}},{"t":52,"s":[100],"i":{"x":[1],"y":[1]},"o":{"x":[0],"y":[0]}},{"t":724,"s":[100],"i":{"x":[1],"y":[1]},"o":{"x":[0],"y":[0]}},{"t":725,"s":[0],"i":{"x":[1],"y":[1]},"o":{"x":[0],"y":[0]}}],"ix":2},"r":{"a":0,"k":0,"ix":2},"p":{"a":0,"k":[0,0],"ix":2},"a":{"a":0,"k":[10000,10000],"ix":2},"s":{"a":0,"k":[100,100],"ix":2}},"ao":0,"ip":0,"op":526.6666666666666,"st":0,"bm":0,"hd":false},{"ddd":0,"refId":"5","w":20000,"h":20000,"ind":14,"ty":0,"nm":"line 4 Outlines (In/Out)","sr":1,"ks":{"o":{"a":1,"k":[{"t":62,"s":[0],"i":{"x":[1],"y":[1]},"o":{"x":[0],"y":[0]}},{"t":63,"s":[100],"i":{"x":[1],"y":[1]},"o":{"x":[0],"y":[0]}},{"t":736,"s":[100],"i":{"x":[1],"y":[1]},"o":{"x":[0],"y":[0]}},{"t":737,"s":[0],"i":{"x":[1],"y":[1]},"o":{"x":[0],"y":[0]}}],"ix":2},"r":{"a":0,"k":0,"ix":2},"p":{"a":0,"k":[0,0],"ix":2},"a":{"a":0,"k":[10000,10000],"ix":2},"s":{"a":0,"k":[100,100],"ix":2}},"ao":0,"ip":0,"op":526.6666666666666,"st":0,"bm":0,"hd":false},{"ddd":0,"refId":"9","w":20000,"h":20000,"ind":28,"ty":0,"nm":"Sombra lupa (Masked Group)","sr":1,"ks":{"o":{"a":0,"k":100,"ix":2},"r":{"a":0,"k":0,"ix":2},"p":{"a":0,"k":[321,321],"ix":2},"a":{"a":0,"k":[10321,10321],"ix":2},"s":{"a":0,"k":[100,100],"ix":2}},"ao":0,"ip":0,"op":526.6666666666666,"st":0,"bm":0,"hd":false},{"ddd":0,"ind":29,"ty":3,"nm":"","sr":1,"ks":{"o":{"a":0,"k":100,"ix":2},"r":{"a":0,"k":0,"ix":2},"p":{"a":0,"k":[321,161.5],"ix":2},"a":{"a":0,"k":[60,60],"ix":2},"s":{"a":0,"k":[100,100],"ix":2}},"ao":0,"ip":0,"op":526.6666666666666,"st":0,"bm":0,"hd":false},{"ddd":0,"refId":"12","w":20000,"h":20000,"ind":36,"ty":0,"nm":"papel bot Outlines (Masked Group) (In/Out)","sr":1,"ks":{"o":{"a":1,"k":[{"t":41,"s":[0],"i":{"x":[1],"y":[1]},"o":{"x":[0],"y":[0]}},{"t":42,"s":[100],"i":{"x":[1],"y":[1]},"o":{"x":[0],"y":[0]}},{"t":701,"s":[100],"i":{"x":[1],"y":[1]},"o":{"x":[0],"y":[0]}},{"t":702,"s":[0],"i":{"x":[1],"y":[1]},"o":{"x":[0],"y":[0]}}],"ix":2},"r":{"a":0,"k":0,"ix":2},"p":{"a":0,"k":[0,0],"ix":2},"a":{"a":0,"k":[10000,10000],"ix":2},"s":{"a":0,"k":[100,100],"ix":2}},"ao":0,"ip":0,"op":526.6666666666666,"st":0,"bm":0,"hd":false,"parent":29},{"ddd":0,"ind":37,"ty":3,"nm":"","sr":1,"ks":{"o":{"a":0,"k":100,"ix":2},"r":{"a":0,"k":0,"ix":2},"p":{"a":0,"k":[321,161.5],"ix":2},"a":{"a":0,"k":[60,60],"ix":2},"s":{"a":0,"k":[100,100],"ix":2}},"ao":0,"ip":0,"op":526.6666666666666,"st":0,"bm":0,"hd":false},{"ddd":0,"refId":"15","w":20000,"h":20000,"ind":53,"ty":0,"nm":"Papel front Outlines (Masked Group) (In/Out)","sr":1,"ks":{"o":{"a":1,"k":[{"t":16,"s":[0],"i":{"x":[1],"y":[1]},"o":{"x":[0],"y":[0]}},{"t":17,"s":[100],"i":{"x":[1],"y":[1]},"o":{"x":[0],"y":[0]}},{"t":701,"s":[100],"i":{"x":[1],"y":[1]},"o":{"x":[0],"y":[0]}},{"t":702,"s":[0],"i":{"x":[1],"y":[1]},"o":{"x":[0],"y":[0]}}],"ix":2},"r":{"a":0,"k":0,"ix":2},"p":{"a":0,"k":[0,0],"ix":2},"a":{"a":0,"k":[10000,10000],"ix":2},"s":{"a":0,"k":[100,100],"ix":2}},"ao":0,"ip":0,"op":526.6666666666666,"st":0,"bm":0,"hd":false,"parent":37},{"ddd":0,"refId":"17","w":20000,"h":20000,"ind":62,"ty":0,"nm":"Papel top Outlines (Masked Group)","sr":1,"ks":{"o":{"a":0,"k":100,"ix":2},"r":{"a":0,"k":0,"ix":2},"p":{"a":0,"k":[211.7120056152344,141.5870056152344],"ix":2},"a":{"a":0,"k":[10000,10000],"ix":2},"s":{"a":0,"k":[200,200],"ix":2}},"ao":0,"ip":0,"op":526.6666666666666,"st":0,"bm":0,"hd":false},{"ddd":0,"refId":"18","w":20000,"h":20000,"ind":65,"ty":0,"nm":"circulito Outlines (In/Out)","sr":1,"ks":{"o":{"a":1,"k":[{"t":386,"s":[0],"i":{"x":[1],"y":[1]},"o":{"x":[0],"y":[0]}},{"t":387,"s":[100],"i":{"x":[1],"y":[1]},"o":{"x":[0],"y":[0]}},{"t":942,"s":[100],"i":{"x":[1],"y":[1]},"o":{"x":[0],"y":[0]}},{"t":943,"s":[0],"i":{"x":[1],"y":[1]},"o":{"x":[0],"y":[0]}}],"ix":2},"r":{"a":0,"k":0,"ix":2},"p":{"a":0,"k":[0,0],"ix":2},"a":{"a":0,"k":[10000,10000],"ix":2},"s":{"a":0,"k":[100,100],"ix":2}},"ao":0,"ip":0,"op":526.6666666666666,"st":0,"bm":0,"hd":false},{"ddd":0,"refId":"19","w":20000,"h":20000,"ind":68,"ty":0,"nm":"x 2 Outlines (In/Out)","sr":1,"ks":{"o":{"a":1,"k":[{"t":419,"s":[0],"i":{"x":[1],"y":[1]},"o":{"x":[0],"y":[0]}},{"t":420,"s":[100],"i":{"x":[1],"y":[1]},"o":{"x":[0],"y":[0]}},{"t":734,"s":[100],"i":{"x":[1],"y":[1]},"o":{"x":[0],"y":[0]}},{"t":735,"s":[0],"i":{"x":[1],"y":[1]},"o":{"x":[0],"y":[0]}}],"ix":2},"r":{"a":0,"k":0,"ix":2},"p":{"a":0,"k":[0,0],"ix":2},"a":{"a":0,"k":[10000,10000],"ix":2},"s":{"a":0,"k":[100,100],"ix":2}},"ao":0,"ip":0,"op":526.6666666666666,"st":0,"bm":0,"hd":false},{"ddd":0,"refId":"20","w":20000,"h":20000,"ind":70,"ty":0,"nm":"bg Outlines","sr":1,"ks":{"o":{"a":1,"k":[{"t":12,"s":[0],"i":{"x":[1],"y":[1]},"o":{"x":[0],"y":[0]}},{"t":82,"s":[100],"i":{"x":[1],"y":[1]},"o":{"x":[0],"y":[0]}}],"ix":2},"r":{"a":0,"k":0,"ix":2},"p":{"a":0,"k":[318.455,325.042],"ix":2},"a":{"a":0,"k":[10119.513,10102.602],"ix":2},"s":{"a":0,"k":[200,200],"ix":2}},"ao":0,"ip":0,"op":526.6666666666666,"st":0,"bm":0,"hd":false}],"markers":[]}